mknodes/__init__.py
mknodes/__main__.py
mknodes/basenodes/__init__.py
mknodes/basenodes/_mkdocstrings/__init__.py
mknodes/basenodes/_mkdocstrings/metadata.toml
mknodes/basenodes/mkadmonition/__init__.py
mknodes/basenodes/mkadmonition/metadata.toml
mknodes/basenodes/mkannotations/__init__.py
mknodes/basenodes/mkannotations/metadata.toml
mknodes/basenodes/mkbasetable/__init__.py
mknodes/basenodes/mkbinaryimage/__init__.py
mknodes/basenodes/mkbinaryimage/metadata.toml
mknodes/basenodes/mkblock/__init__.py
mknodes/basenodes/mkblockquote/__init__.py
mknodes/basenodes/mkblockquote/metadata.toml
mknodes/basenodes/mkcard/__init__.py
mknodes/basenodes/mkcard/grid.css
mknodes/basenodes/mkcard/metadata.toml
mknodes/basenodes/mkclidoc/__init__.py
mknodes/basenodes/mkclidoc/metadata.toml
mknodes/basenodes/mkcode/__init__.py
mknodes/basenodes/mkcode/metadata.toml
mknodes/basenodes/mkcompactadmonition/__init__.py
mknodes/basenodes/mkcompactadmonition/compactadmonition.css
mknodes/basenodes/mkcompactadmonition/metadata.toml
mknodes/basenodes/mkcontainer/__init__.py
mknodes/basenodes/mkcontainer/metadata.toml
mknodes/basenodes/mkcritic/__init__.py
mknodes/basenodes/mkcritic/metadata.toml
mknodes/basenodes/mkdataclassinfo/__init__.py
mknodes/basenodes/mkdataclassinfo/metadata.toml
mknodes/basenodes/mkdefinitionlist/__init__.py
mknodes/basenodes/mkdefinitionlist/metadata.toml
mknodes/basenodes/mkdetailsblock/__init__.py
mknodes/basenodes/mkdetailsblock/metadata.toml
mknodes/basenodes/mkdiagram/__init__.py
mknodes/basenodes/mkdiagram/metadata.toml
mknodes/basenodes/mkfootnotes/__init__.py
mknodes/basenodes/mkfootnotes/metadata.toml
mknodes/basenodes/mkheader/__init__.py
mknodes/basenodes/mkheader/metadata.toml
mknodes/basenodes/mkhtmlblock/__init__.py
mknodes/basenodes/mkhtmlblock/metadata.toml
mknodes/basenodes/mkhtmltable/__init__.py
mknodes/basenodes/mkhtmltable/metadata.toml
mknodes/basenodes/mkicon/__init__.py
mknodes/basenodes/mkicon/metadata.toml
mknodes-2.2.12.dist-info/WHEEL
mknodes-2.2.12.dist-info/entry_points.txt
mknodes-2.2.12.dist-info/METADATA
mknodes-2.2.12.dist-info/RECORD
