Metadata-Version: 2.3
Name: mknodes
Version: 2.2.12
Summary: Don't write docs. Code them.
Keywords: docs,docstrings,documentation,framework,internet,markdown
Author: Philipp Temminghoff
Author-email: Philipp Temminghoff <philipptemminghoff@gmail.com>
License: MIT License
Classifier: Development Status :: 4 - Beta
Classifier: Framework :: MkDocs
Classifier: Intended Audience :: Developers
Classifier: Operating System :: OS Independent
Classifier: Programming Language :: Python :: 3
Classifier: Programming Language :: Python :: 3 :: Only
Classifier: Programming Language :: Python :: 3.12
Classifier: Programming Language :: Python :: 3.13
Classifier: Programming Language :: Python :: 3.14
Classifier: Programming Language :: Python :: Implementation :: CPython
Classifier: Topic :: Documentation
Classifier: Topic :: Internet
Classifier: Topic :: Software Development :: Documentation
Classifier: Topic :: Software Development :: User Interfaces
Classifier: Topic :: Text Processing :: Markup :: Markdown
Requires-Dist: agentpool[default]>=0.99.54
Requires-Dist: anybadge
Requires-Dist: anyenv[httpx]>=1.9.0
Requires-Dist: clinspector
Requires-Dist: coloraide
Requires-Dist: epregistry
Requires-Dist: fieldz
Requires-Dist: fsspec
Requires-Dist: git-changelog
Requires-Dist: githarbor
Requires-Dist: gitpython
Requires-Dist: griffe
Requires-Dist: jinja2
Requires-Dist: jinjarope[icons]
Requires-Dist: mkdocstrings[python]
Requires-Dist: natsort
Requires-Dist: pipdeptree
Requires-Dist: pydantic
Requires-Dist: pytest-asyncio>=1.3.0
Requires-Dist: python-dotenv
Requires-Dist: setuptools>=80.9.0
Requires-Dist: tomli-w
Requires-Dist: typer>=0.12.0
Requires-Dist: universal-pathlib
Requires-Dist: upathtools[httpx]
Requires-Dist: yamling
Requires-Dist: zensical>=0.0.11
Requires-Dist: agentpool[default] ; extra == 'llm'
Requires-Python: >=3.13
Project-URL: Code coverage, https://app.codecov.io/gh/phil65/mknodes
Project-URL: Discussions, https://github.com/phil65/mknodes/discussions
Project-URL: Documentation, https://phil65.github.io/mknodes/
Project-URL: Issues, https://github.com/phil65/mknodes/issues
Project-URL: Source, https://github.com/phil65/mknodes
Provides-Extra: llm
